appconfig_helper/__init__.py
appconfig_helper/appconfig_helper.py
appconfig_helper/py.typed
appconfig_helper/version.py
sample_helper_aws_appconfig-2.3.0.dist-info/METADATA
sample_helper_aws_appconfig-2.3.0.dist-info/WHEEL
sample_helper_aws_appconfig-2.3.0.dist-info/licenses/LICENSE
sample_helper_aws_appconfig-2.3.0.dist-info/licenses/NOTICE
sample_helper_aws_appconfig-2.3.0.dist-info/RECORD
