Metadata-Version: 2.4
Name: sample-helper-aws-appconfig
Version: 2.3.0
Summary: Sample helper library for AWS AppConfig
License: OSI Approved (Apache-2.0)
License-File: LICENSE
License-File: NOTICE
Keywords: aws,appconfig
Author: Amazon Web Services
Maintainer: James Seward
Maintainer-email: sewardjm@amazon.co.uk
Requires-Python: >=3.10,<4.0
Classifier: Development Status :: 4 - Beta
Classifier: Intended Audience :: Developers
Classifier: License :: OSI Approved
Classifier: License :: Other/Proprietary License
Classifier: Programming Language :: Python :: 3
Classifier: Programming Language :: Python :: 3.10
Classifier: Programming Language :: Python :: 3.11
Classifier: Programming Language :: Python :: 3.12
Classifier: Programming Language :: Python :: 3.13
Classifier: Programming Language :: Python :: 3.14
Classifier: Typing :: Typed
Requires-Dist: PyYAML (>=6.0,<7.0)
Requires-Dist: boto3 (>=1.42.4,<2.0.0)
Requires-Dist: botocore[crt] (>=1.42.4,<2.0.0)
Requires-Dist: urllib3 (>=2.6.0,<3.0.0)
Project-URL: Repository, https://github.com/aws-samples/sample-python-helper-aws-appconfig
